{
  "billable": {
    "UBUNTU": {
      "total_ms": 0,
      "jobs": 134,
      "job_runs": [
        {
          "job_id": 13253272815,
          "duration_ms": 0
        },
        {
          "job_id": 13253273384,
          "duration_ms": 0
        },
        {
          "job_id": 13253273823,
          "duration_ms": 0
        },
        {
          "job_id": 13253274068,
          "duration_ms": 0
        },
        {
          "job_id": 13253274325,
          "duration_ms": 0
        },
        {
          "job_id": 13253274655,
          "duration_ms": 0
        },
        {
          "job_id": 13253274782,
          "duration_ms": 0
        },
        {
          "job_id": 13253274898,
          "duration_ms": 0
        },
        {
          "job_id": 13253275002,
          "duration_ms": 0
        },
        {
          "job_id": 13253275106,
          "duration_ms": 0
        },
        {
          "job_id": 13253275202,
          "duration_ms": 0
        },
        {
          "job_id": 13253275290,
          "duration_ms": 0
        },
        {
          "job_id": 13253275426,
          "duration_ms": 0
        },
        {
          "job_id": 13253275644,
          "duration_ms": 0
        },
        {
          "job_id": 13253275758,
          "duration_ms": 0
        },
        {
          "job_id": 13253275889,
          "duration_ms": 0
        },
        {
          "job_id": 13253275989,
          "duration_ms": 0
        },
        {
          "job_id": 13253276095,
          "duration_ms": 0
        },
        {
          "job_id": 13253276199,
          "duration_ms": 0
        },
        {
          "job_id": 13253276348,
          "duration_ms": 0
        },
        {
          "job_id": 13253276467,
          "duration_ms": 0
        },
        {
          "job_id": 13253276569,
          "duration_ms": 0
        },
        {
          "job_id": 13253418618,
          "duration_ms": 0
        },
        {
          "job_id": 13253418858,
          "duration_ms": 0
        },
        {
          "job_id": 13253418977,
          "duration_ms": 0
        },
        {
          "job_id": 13253419096,
          "duration_ms": 0
        },
        {
          "job_id": 13253419203,
          "duration_ms": 0
        },
        {
          "job_id": 13253419312,
          "duration_ms": 0
        },
        {
          "job_id": 13253419454,
          "duration_ms": 0
        },
        {
          "job_id": 13253419587,
          "duration_ms": 0
        },
        {
          "job_id": 13253419792,
          "duration_ms": 0
        },
        {
          "job_id": 13253420038,
          "duration_ms": 0
        },
        {
          "job_id": 13253420227,
          "duration_ms": 0
        },
        {
          "job_id": 13253420334,
          "duration_ms": 0
        },
        {
          "job_id": 13253420445,
          "duration_ms": 0
        },
        {
          "job_id": 13253420553,
          "duration_ms": 0
        },
        {
          "job_id": 13253420650,
          "duration_ms": 0
        },
        {
          "job_id": 13253420762,
          "duration_ms": 0
        },
        {
          "job_id": 13253420882,
          "duration_ms": 0
        },
        {
          "job_id": 13253420977,
          "duration_ms": 0
        },
        {
          "job_id": 13253421102,
          "duration_ms": 0
        },
        {
          "job_id": 13253421209,
          "duration_ms": 0
        },
        {
          "job_id": 13253421335,
          "duration_ms": 0
        },
        {
          "job_id": 13253421444,
          "duration_ms": 0
        },
        {
          "job_id": 13253421548,
          "duration_ms": 0
        },
        {
          "job_id": 13253421677,
          "duration_ms": 0
        },
        {
          "job_id": 13253421778,
          "duration_ms": 0
        },
        {
          "job_id": 13253421893,
          "duration_ms": 0
        },
        {
          "job_id": 13253421991,
          "duration_ms": 0
        },
        {
          "job_id": 13253422084,
          "duration_ms": 0
        },
        {
          "job_id": 13253422161,
          "duration_ms": 0
        },
        {
          "job_id": 13253422285,
          "duration_ms": 0
        },
        {
          "job_id": 13253422393,
          "duration_ms": 0
        },
        {
          "job_id": 13253422496,
          "duration_ms": 0
        },
        {
          "job_id": 13253422581,
          "duration_ms": 0
        },
        {
          "job_id": 13253422665,
          "duration_ms": 0
        },
        {
          "job_id": 13253422753,
          "duration_ms": 0
        },
        {
          "job_id": 13253422863,
          "duration_ms": 0
        },
        {
          "job_id": 13253422956,
          "duration_ms": 0
        },
        {
          "job_id": 13253423060,
          "duration_ms": 0
        },
        {
          "job_id": 13253423156,
          "duration_ms": 0
        },
        {
          "job_id": 13253423258,
          "duration_ms": 0
        },
        {
          "job_id": 13253423349,
          "duration_ms": 0
        },
        {
          "job_id": 13253423428,
          "duration_ms": 0
        },
        {
          "job_id": 13253423506,
          "duration_ms": 0
        },
        {
          "job_id": 13253423593,
          "duration_ms": 0
        },
        {
          "job_id": 13253423688,
          "duration_ms": 0
        },
        {
          "job_id": 13289020291,
          "duration_ms": 0
        },
        {
          "job_id": 13289020406,
          "duration_ms": 0
        },
        {
          "job_id": 13289020527,
          "duration_ms": 0
        },
        {
          "job_id": 13289020627,
          "duration_ms": 0
        },
        {
          "job_id": 13289020775,
          "duration_ms": 0
        },
        {
          "job_id": 13289020888,
          "duration_ms": 0
        },
        {
          "job_id": 13289021006,
          "duration_ms": 0
        },
        {
          "job_id": 13289021138,
          "duration_ms": 0
        },
        {
          "job_id": 13289021218,
          "duration_ms": 0
        },
        {
          "job_id": 13289021313,
          "duration_ms": 0
        },
        {
          "job_id": 13289021401,
          "duration_ms": 0
        },
        {
          "job_id": 13289021513,
          "duration_ms": 0
        },
        {
          "job_id": 13289021604,
          "duration_ms": 0
        },
        {
          "job_id": 13289021682,
          "duration_ms": 0
        },
        {
          "job_id": 13289021994,
          "duration_ms": 0
        },
        {
          "job_id": 13289022068,
          "duration_ms": 0
        },
        {
          "job_id": 13289022136,
          "duration_ms": 0
        },
        {
          "job_id": 13289022194,
          "duration_ms": 0
        },
        {
          "job_id": 13289022269,
          "duration_ms": 0
        },
        {
          "job_id": 13289022334,
          "duration_ms": 0
        },
        {
          "job_id": 13289022410,
          "duration_ms": 0
        },
        {
          "job_id": 13289022479,
          "duration_ms": 0
        },
        {
          "job_id": 13289022901,
          "duration_ms": 0
        },
        {
          "job_id": 13289022958,
          "duration_ms": 0
        },
        {
          "job_id": 13289023020,
          "duration_ms": 0
        },
        {
          "job_id": 13289023078,
          "duration_ms": 0
        },
        {
          "job_id": 13289023128,
          "duration_ms": 0
        },
        {
          "job_id": 13289023157,
          "duration_ms": 0
        },
        {
          "job_id": 13289023193,
          "duration_ms": 0
        },
        {
          "job_id": 13289023222,
          "duration_ms": 0
        },
        {
          "job_id": 13289023247,
          "duration_ms": 0
        },
        {
          "job_id": 13289023279,
          "duration_ms": 0
        },
        {
          "job_id": 13289023302,
          "duration_ms": 0
        },
        {
          "job_id": 13289023334,
          "duration_ms": 0
        },
        {
          "job_id": 13289023365,
          "duration_ms": 0
        },
        {
          "job_id": 13289023393,
          "duration_ms": 0
        },
        {
          "job_id": 13289023418,
          "duration_ms": 0
        },
        {
          "job_id": 13289023444,
          "duration_ms": 0
        },
        {
          "job_id": 13289023483,
          "duration_ms": 0
        },
        {
          "job_id": 13289023510,
          "duration_ms": 0
        },
        {
          "job_id": 13289023543,
          "duration_ms": 0
        },
        {
          "job_id": 13289023580,
          "duration_ms": 0
        },
        {
          "job_id": 13289023616,
          "duration_ms": 0
        },
        {
          "job_id": 13289023653,
          "duration_ms": 0
        },
        {
          "job_id": 13289023678,
          "duration_ms": 0
        },
        {
          "job_id": 13289023707,
          "duration_ms": 0
        },
        {
          "job_id": 13289023736,
          "duration_ms": 0
        },
        {
          "job_id": 13289023773,
          "duration_ms": 0
        },
        {
          "job_id": 13289023801,
          "duration_ms": 0
        },
        {
          "job_id": 13289023831,
          "duration_ms": 0
        },
        {
          "job_id": 13289023871,
          "duration_ms": 0
        },
        {
          "job_id": 13289023916,
          "duration_ms": 0
        },
        {
          "job_id": 13289023957,
          "duration_ms": 0
        },
        {
          "job_id": 13289023997,
          "duration_ms": 0
        },
        {
          "job_id": 13289024040,
          "duration_ms": 0
        },
        {
          "job_id": 13289024104,
          "duration_ms": 0
        },
        {
          "job_id": 13289024154,
          "duration_ms": 0
        },
        {
          "job_id": 13289024209,
          "duration_ms": 0
        },
        {
          "job_id": 13289024259,
          "duration_ms": 0
        },
        {
          "job_id": 13289024299,
          "duration_ms": 0
        },
        {
          "job_id": 13289024341,
          "duration_ms": 0
        },
        {
          "job_id": 13289024374,
          "duration_ms": 0
        },
        {
          "job_id": 13289024422,
          "duration_ms": 0
        },
        {
          "job_id": 13289024475,
          "duration_ms": 0
        },
        {
          "job_id": 13289024526,
          "duration_ms": 0
        },
        {
          "job_id": 13289024584,
          "duration_ms": 0
        },
        {
          "job_id": 13289024659,
          "duration_ms": 0
        }
      ]
    }
  },
  "run_duration_ms": 21633000
}
