{
  "billable": {
    "UBUNTU": {
      "total_ms": 0,
      "jobs": 6,
      "job_runs": [
        {
          "job_id": 11668734220,
          "duration_ms": 0
        },
        {
          "job_id": 11668734461,
          "duration_ms": 0
        },
        {
          "job_id": 11668734640,
          "duration_ms": 0
        },
        {
          "job_id": 11668734833,
          "duration_ms": 0
        },
        {
          "job_id": 11668735022,
          "duration_ms": 0
        },
        {
          "job_id": 11668735238,
          "duration_ms": 0
        }
      ]
    }
  },
  "run_duration_ms": 37000
}
