{
  "billable": {
    "UBUNTU": {
      "total_ms": 0,
      "jobs": 33,
      "job_runs": [
        {
          "job_id": 11425609719,
          "duration_ms": 0
        },
        {
          "job_id": 11425732853,
          "duration_ms": 0
        },
        {
          "job_id": 11425733110,
          "duration_ms": 0
        },
        {
          "job_id": 11425733269,
          "duration_ms": 0
        },
        {
          "job_id": 11425733470,
          "duration_ms": 0
        },
        {
          "job_id": 11425733599,
          "duration_ms": 0
        },
        {
          "job_id": 11425733753,
          "duration_ms": 0
        },
        {
          "job_id": 11425733924,
          "duration_ms": 0
        },
        {
          "job_id": 11425734138,
          "duration_ms": 0
        },
        {
          "job_id": 11425734318,
          "duration_ms": 0
        },
        {
          "job_id": 11425734539,
          "duration_ms": 0
        },
        {
          "job_id": 11428871121,
          "duration_ms": 0
        },
        {
          "job_id": 11428872850,
          "duration_ms": 0
        },
        {
          "job_id": 11428872978,
          "duration_ms": 0
        },
        {
          "job_id": 11428873186,
          "duration_ms": 0
        },
        {
          "job_id": 11428873283,
          "duration_ms": 0
        },
        {
          "job_id": 11428873388,
          "duration_ms": 0
        },
        {
          "job_id": 11428873516,
          "duration_ms": 0
        },
        {
          "job_id": 11428873671,
          "duration_ms": 0
        },
        {
          "job_id": 11428873837,
          "duration_ms": 0
        },
        {
          "job_id": 11428873955,
          "duration_ms": 0
        },
        {
          "job_id": 11428874089,
          "duration_ms": 0
        },
        {
          "job_id": 11428887185,
          "duration_ms": 0
        },
        {
          "job_id": 11428887506,
          "duration_ms": 0
        },
        {
          "job_id": 11428887665,
          "duration_ms": 0
        },
        {
          "job_id": 11428887835,
          "duration_ms": 0
        },
        {
          "job_id": 11428887960,
          "duration_ms": 0
        },
        {
          "job_id": 11428888093,
          "duration_ms": 0
        },
        {
          "job_id": 11428888240,
          "duration_ms": 0
        },
        {
          "job_id": 11428888368,
          "duration_ms": 0
        },
        {
          "job_id": 11428888501,
          "duration_ms": 0
        },
        {
          "job_id": 11428888641,
          "duration_ms": 0
        },
        {
          "job_id": 11428888786,
          "duration_ms": 0
        }
      ]
    }
  },
  "run_duration_ms": 928000
}
