{
  "id": 3853761332,
  "name": "Aries-Askar",
  "node_id": "WFR_kwLOD6QZ4s7ls7s0",
  "head_branch": "main",
  "head_sha": "82616e69d8861951bbddc4d79b58675898c96ece",
  "path": ".github/workflows/build.yml",
  "display_title": "Added .net wrapper",
  "run_number": 162,
  "event": "pull_request",
  "status": "completed",
  "conclusion": "failure",
  "workflow_id": 3766130,
  "check_suite_id": 10216873343,
  "check_suite_node_id": "CS_kwDOD6QZ4s8AAAACYPkdfw",
  "url": "https://api.github.com/repos/hyperledger/aries-askar/actions/runs/3853761332",
  "html_url": "https://github.com/hyperledger/aries-askar/actions/runs/3853761332",
  "pull_requests": [],
  "created_at": "2023-01-06T08:23:05Z",
  "updated_at": "2023-01-06T08:58:44Z",
  "actor": {
    "login": "CHempel-esatus",
    "id": 53933121,
    "node_id": "MDQ6VXNlcjUzOTMzMTIx",
    "avatar_url": "https://avatars.githubusercontent.com/u/53933121?v=4",
    "gravatar_id": "",
    "url": "https://api.github.com/users/CHempel-esatus",
    "html_url": "https://github.com/CHempel-esatus",
    "followers_url": "https://api.github.com/users/CHempel-esatus/followers",
    "following_url": "https://api.github.com/users/CHempel-esatus/following{/other_user}",
    "gists_url": "https://api.github.com/users/CHempel-esatus/gists{/gist_id}",
    "starred_url": "https://api.github.com/users/CHempel-esatus/starred{/owner}{/repo}",
    "subscriptions_url": "https://api.github.com/users/CHempel-esatus/subscriptions",
    "organizations_url": "https://api.github.com/users/CHempel-esatus/orgs",
    "repos_url": "https://api.github.com/users/CHempel-esatus/repos",
    "events_url": "https://api.github.com/users/CHempel-esatus/events{/privacy}",
    "received_events_url": "https://api.github.com/users/CHempel-esatus/received_events",
    "type": "User",
    "site_admin": false
  },
  "run_attempt": 1,
  "referenced_workflows": [],
  "run_started_at": "2023-01-06T08:23:05Z",
  "triggering_actor": {
    "login": "CHempel-esatus",
    "id": 53933121,
    "node_id": "MDQ6VXNlcjUzOTMzMTIx",
    "avatar_url": "https://avatars.githubusercontent.com/u/53933121?v=4",
    "gravatar_id": "",
    "url": "https://api.github.com/users/CHempel-esatus",
    "html_url": "https://github.com/CHempel-esatus",
    "followers_url": "https://api.github.com/users/CHempel-esatus/followers",
    "following_url": "https://api.github.com/users/CHempel-esatus/following{/other_user}",
    "gists_url": "https://api.github.com/users/CHempel-esatus/gists{/gist_id}",
    "starred_url": "https://api.github.com/users/CHempel-esatus/starred{/owner}{/repo}",
    "subscriptions_url": "https://api.github.com/users/CHempel-esatus/subscriptions",
    "organizations_url": "https://api.github.com/users/CHempel-esatus/orgs",
    "repos_url": "https://api.github.com/users/CHempel-esatus/repos",
    "events_url": "https://api.github.com/users/CHempel-esatus/events{/privacy}",
    "received_events_url": "https://api.github.com/users/CHempel-esatus/received_events",
    "type": "User",
    "site_admin": false
  },
  "jobs_url": "https://api.github.com/repos/hyperledger/aries-askar/actions/runs/3853761332/jobs",
  "logs_url": "https://api.github.com/repos/hyperledger/aries-askar/actions/runs/3853761332/logs",
  "check_suite_url": "https://api.github.com/repos/hyperledger/aries-askar/check-suites/10216873343",
  "artifacts_url": "https://api.github.com/repos/hyperledger/aries-askar/actions/runs/3853761332/artifacts",
  "cancel_url": "https://api.github.com/repos/hyperledger/aries-askar/actions/runs/3853761332/cancel",
  "rerun_url": "https://api.github.com/repos/hyperledger/aries-askar/actions/runs/3853761332/rerun",
  "previous_attempt_url": null,
  "workflow_url": "https://api.github.com/repos/hyperledger/aries-askar/actions/workflows/3766130",
  "head_commit": {
    "id": "82616e69d8861951bbddc4d79b58675898c96ece",
    "tree_id": "ff07a6cad3edcf3c63478578950df3bb897df929",
    "message": "Merge branch 'hyperledger:main' into main",
    "timestamp": "2023-01-06T08:23:01Z",
    "author": {
      "name": "Christopher Hempel",
      "email": "53933121+CHempel-esatus@users.noreply.github.com"
    },
    "committer": {
      "name": "GitHub",
      "email": "noreply@github.com"
    }
  },
  "repository": {
    "id": 262412770,
    "node_id": "MDEwOlJlcG9zaXRvcnkyNjI0MTI3NzA=",
    "name": "aries-askar",
    "full_name": "hyperledger/aries-askar",
    "private": false,
    "owner": {
      "login": "hyperledger",
      "id": 7657900,
      "node_id": "MDEyOk9yZ2FuaXphdGlvbjc2NTc5MDA=",
      "avatar_url": "https://avatars.githubusercontent.com/u/7657900?v=4",
      "gravatar_id": "",
      "url": "https://api.github.com/users/hyperledger",
      "html_url": "https://github.com/hyperledger",
      "followers_url": "https://api.github.com/users/hyperledger/followers",
      "following_url": "https://api.github.com/users/hyperledger/following{/other_user}",
      "gists_url": "https://api.github.com/users/hyperledger/gists{/gist_id}",
      "starred_url": "https://api.github.com/users/hyperledger/starred{/owner}{/repo}",
      "subscriptions_url": "https://api.github.com/users/hyperledger/subscriptions",
      "organizations_url": "https://api.github.com/users/hyperledger/orgs",
      "repos_url": "https://api.github.com/users/hyperledger/repos",
      "events_url": "https://api.github.com/users/hyperledger/events{/privacy}",
      "received_events_url": "https://api.github.com/users/hyperledger/received_events",
      "type": "Organization",
      "site_admin": false
    },
    "html_url": "https://github.com/hyperledger/aries-askar",
    "description": "Secure storage designed for Hyperledger Aries agents.",
    "fork": false,
    "url": "https://api.github.com/repos/hyperledger/aries-askar",
    "forks_url": "https://api.github.com/repos/hyperledger/aries-askar/forks",
    "keys_url": "https://api.github.com/repos/hyperledger/aries-askar/keys{/key_id}",
    "collaborators_url": "https://api.github.com/repos/hyperledger/aries-askar/collaborators{/collaborator}",
    "teams_url": "https://api.github.com/repos/hyperledger/aries-askar/teams",
    "hooks_url": "https://api.github.com/repos/hyperledger/aries-askar/hooks",
    "issue_events_url": "https://api.github.com/repos/hyperledger/aries-askar/issues/events{/number}",
    "events_url": "https://api.github.com/repos/hyperledger/aries-askar/events",
    "assignees_url": "https://api.github.com/repos/hyperledger/aries-askar/assignees{/user}",
    "branches_url": "https://api.github.com/repos/hyperledger/aries-askar/branches{/branch}",
    "tags_url": "https://api.github.com/repos/hyperledger/aries-askar/tags",
    "blobs_url": "https://api.github.com/repos/hyperledger/aries-askar/git/blobs{/sha}",
    "git_tags_url": "https://api.github.com/repos/hyperledger/aries-askar/git/tags{/sha}",
    "git_refs_url": "https://api.github.com/repos/hyperledger/aries-askar/git/refs{/sha}",
    "trees_url": "https://api.github.com/repos/hyperledger/aries-askar/git/trees{/sha}",
    "statuses_url": "https://api.github.com/repos/hyperledger/aries-askar/statuses/{sha}",
    "languages_url": "https://api.github.com/repos/hyperledger/aries-askar/languages",
    "stargazers_url": "https://api.github.com/repos/hyperledger/aries-askar/stargazers",
    "contributors_url": "https://api.github.com/repos/hyperledger/aries-askar/contributors",
    "subscribers_url": "https://api.github.com/repos/hyperledger/aries-askar/subscribers",
    "subscription_url": "https://api.github.com/repos/hyperledger/aries-askar/subscription",
    "commits_url": "https://api.github.com/repos/hyperledger/aries-askar/commits{/sha}",
    "git_commits_url": "https://api.github.com/repos/hyperledger/aries-askar/git/commits{/sha}",
    "comments_url": "https://api.github.com/repos/hyperledger/aries-askar/comments{/number}",
    "issue_comment_url": "https://api.github.com/repos/hyperledger/aries-askar/issues/comments{/number}",
    "contents_url": "https://api.github.com/repos/hyperledger/aries-askar/contents/{+path}",
    "compare_url": "https://api.github.com/repos/hyperledger/aries-askar/compare/{base}...{head}",
    "merges_url": "https://api.github.com/repos/hyperledger/aries-askar/merges",
    "archive_url": "https://api.github.com/repos/hyperledger/aries-askar/{archive_format}{/ref}",
    "downloads_url": "https://api.github.com/repos/hyperledger/aries-askar/downloads",
    "issues_url": "https://api.github.com/repos/hyperledger/aries-askar/issues{/number}",
    "pulls_url": "https://api.github.com/repos/hyperledger/aries-askar/pulls{/number}",
    "milestones_url": "https://api.github.com/repos/hyperledger/aries-askar/milestones{/number}",
    "notifications_url": "https://api.github.com/repos/hyperledger/aries-askar/notifications{?since,all,participating}",
    "labels_url": "https://api.github.com/repos/hyperledger/aries-askar/labels{/name}",
    "releases_url": "https://api.github.com/repos/hyperledger/aries-askar/releases{/id}",
    "deployments_url": "https://api.github.com/repos/hyperledger/aries-askar/deployments"
  },
  "head_repository": {
    "id": 490994502,
    "node_id": "R_kgDOHUP7Rg",
    "name": "aries-askar",
    "full_name": "esatus/aries-askar",
    "private": false,
    "owner": {
      "login": "esatus",
      "id": 80454404,
      "node_id": "MDEyOk9yZ2FuaXphdGlvbjgwNDU0NDA0",
      "avatar_url": "https://avatars.githubusercontent.com/u/80454404?v=4",
      "gravatar_id": "",
      "url": "https://api.github.com/users/esatus",
      "html_url": "https://github.com/esatus",
      "followers_url": "https://api.github.com/users/esatus/followers",
      "following_url": "https://api.github.com/users/esatus/following{/other_user}",
      "gists_url": "https://api.github.com/users/esatus/gists{/gist_id}",
      "starred_url": "https://api.github.com/users/esatus/starred{/owner}{/repo}",
      "subscriptions_url": "https://api.github.com/users/esatus/subscriptions",
      "organizations_url": "https://api.github.com/users/esatus/orgs",
      "repos_url": "https://api.github.com/users/esatus/repos",
      "events_url": "https://api.github.com/users/esatus/events{/privacy}",
      "received_events_url": "https://api.github.com/users/esatus/received_events",
      "type": "Organization",
      "site_admin": false
    },
    "html_url": "https://github.com/esatus/aries-askar",
    "description": "Secure storage designed for Hyperledger Aries agents.",
    "fork": true,
    "url": "https://api.github.com/repos/esatus/aries-askar",
    "forks_url": "https://api.github.com/repos/esatus/aries-askar/forks",
    "keys_url": "https://api.github.com/repos/esatus/aries-askar/keys{/key_id}",
    "collaborators_url": "https://api.github.com/repos/esatus/aries-askar/collaborators{/collaborator}",
    "teams_url": "https://api.github.com/repos/esatus/aries-askar/teams",
    "hooks_url": "https://api.github.com/repos/esatus/aries-askar/hooks",
    "issue_events_url": "https://api.github.com/repos/esatus/aries-askar/issues/events{/number}",
    "events_url": "https://api.github.com/repos/esatus/aries-askar/events",
    "assignees_url": "https://api.github.com/repos/esatus/aries-askar/assignees{/user}",
    "branches_url": "https://api.github.com/repos/esatus/aries-askar/branches{/branch}",
    "tags_url": "https://api.github.com/repos/esatus/aries-askar/tags",
    "blobs_url": "https://api.github.com/repos/esatus/aries-askar/git/blobs{/sha}",
    "git_tags_url": "https://api.github.com/repos/esatus/aries-askar/git/tags{/sha}",
    "git_refs_url": "https://api.github.com/repos/esatus/aries-askar/git/refs{/sha}",
    "trees_url": "https://api.github.com/repos/esatus/aries-askar/git/trees{/sha}",
    "statuses_url": "https://api.github.com/repos/esatus/aries-askar/statuses/{sha}",
    "languages_url": "https://api.github.com/repos/esatus/aries-askar/languages",
    "stargazers_url": "https://api.github.com/repos/esatus/aries-askar/stargazers",
    "contributors_url": "https://api.github.com/repos/esatus/aries-askar/contributors",
    "subscribers_url": "https://api.github.com/repos/esatus/aries-askar/subscribers",
    "subscription_url": "https://api.github.com/repos/esatus/aries-askar/subscription",
    "commits_url": "https://api.github.com/repos/esatus/aries-askar/commits{/sha}",
    "git_commits_url": "https://api.github.com/repos/esatus/aries-askar/git/commits{/sha}",
    "comments_url": "https://api.github.com/repos/esatus/aries-askar/comments{/number}",
    "issue_comment_url": "https://api.github.com/repos/esatus/aries-askar/issues/comments{/number}",
    "contents_url": "https://api.github.com/repos/esatus/aries-askar/contents/{+path}",
    "compare_url": "https://api.github.com/repos/esatus/aries-askar/compare/{base}...{head}",
    "merges_url": "https://api.github.com/repos/esatus/aries-askar/merges",
    "archive_url": "https://api.github.com/repos/esatus/aries-askar/{archive_format}{/ref}",
    "downloads_url": "https://api.github.com/repos/esatus/aries-askar/downloads",
    "issues_url": "https://api.github.com/repos/esatus/aries-askar/issues{/number}",
    "pulls_url": "https://api.github.com/repos/esatus/aries-askar/pulls{/number}",
    "milestones_url": "https://api.github.com/repos/esatus/aries-askar/milestones{/number}",
    "notifications_url": "https://api.github.com/repos/esatus/aries-askar/notifications{?since,all,participating}",
    "labels_url": "https://api.github.com/repos/esatus/aries-askar/labels{/name}",
    "releases_url": "https://api.github.com/repos/esatus/aries-askar/releases{/id}",
    "deployments_url": "https://api.github.com/repos/esatus/aries-askar/deployments"
  }
}
