{
  "billable": {
    "UBUNTU": {
      "total_ms": 0,
      "jobs": 11,
      "job_runs": [
        {
          "job_id": 11224207104,
          "duration_ms": 0
        },
        {
          "job_id": 11227295888,
          "duration_ms": 0
        },
        {
          "job_id": 11227296344,
          "duration_ms": 0
        },
        {
          "job_id": 11227296783,
          "duration_ms": 0
        },
        {
          "job_id": 11227297226,
          "duration_ms": 0
        },
        {
          "job_id": 11227297526,
          "duration_ms": 0
        },
        {
          "job_id": 11227297880,
          "duration_ms": 0
        },
        {
          "job_id": 11227298261,
          "duration_ms": 0
        },
        {
          "job_id": 11227298671,
          "duration_ms": 0
        },
        {
          "job_id": 11227298954,
          "duration_ms": 0
        },
        {
          "job_id": 11227299283,
          "duration_ms": 0
        }
      ]
    }
  },
  "run_duration_ms": 8937000
}
