{
  "billable": {
    "UBUNTU": {
      "total_ms": 0,
      "jobs": 11,
      "job_runs": [
        {
          "job_id": 9978691934,
          "duration_ms": 0
        },
        {
          "job_id": 9978692124,
          "duration_ms": 0
        },
        {
          "job_id": 9978760670,
          "duration_ms": 0
        },
        {
          "job_id": 9978761082,
          "duration_ms": 0
        },
        {
          "job_id": 9978761295,
          "duration_ms": 0
        },
        {
          "job_id": 9978761476,
          "duration_ms": 0
        },
        {
          "job_id": 9978761668,
          "duration_ms": 0
        },
        {
          "job_id": 9978761852,
          "duration_ms": 0
        },
        {
          "job_id": 9978762041,
          "duration_ms": 0
        },
        {
          "job_id": 9978762240,
          "duration_ms": 0
        },
        {
          "job_id": 9978762454,
          "duration_ms": 0
        }
      ]
    }
  },
  "run_duration_ms": 1097000
}
