{
  "billable": {
    "UBUNTU": {
      "total_ms": 0,
      "jobs": 67,
      "job_runs": [
        {
          "job_id": 12862825581,
          "duration_ms": 0
        },
        {
          "job_id": 12862825990,
          "duration_ms": 0
        },
        {
          "job_id": 12862837127,
          "duration_ms": 0
        },
        {
          "job_id": 12863003739,
          "duration_ms": 0
        },
        {
          "job_id": 12863004118,
          "duration_ms": 0
        },
        {
          "job_id": 12863016015,
          "duration_ms": 0
        },
        {
          "job_id": 12863016323,
          "duration_ms": 0
        },
        {
          "job_id": 12863090412,
          "duration_ms": 0
        },
        {
          "job_id": 12863090693,
          "duration_ms": 0
        },
        {
          "job_id": 12863090864,
          "duration_ms": 0
        },
        {
          "job_id": 12863091077,
          "duration_ms": 0
        },
        {
          "job_id": 12863091347,
          "duration_ms": 0
        },
        {
          "job_id": 12863091593,
          "duration_ms": 0
        },
        {
          "job_id": 12863091817,
          "duration_ms": 0
        },
        {
          "job_id": 12863092088,
          "duration_ms": 0
        },
        {
          "job_id": 12863092404,
          "duration_ms": 0
        },
        {
          "job_id": 12863092640,
          "duration_ms": 0
        },
        {
          "job_id": 12863092863,
          "duration_ms": 0
        },
        {
          "job_id": 12863093078,
          "duration_ms": 0
        },
        {
          "job_id": 12863093336,
          "duration_ms": 0
        },
        {
          "job_id": 12863093587,
          "duration_ms": 0
        },
        {
          "job_id": 12863093786,
          "duration_ms": 0
        },
        {
          "job_id": 12866634399,
          "duration_ms": 0
        },
        {
          "job_id": 12866634893,
          "duration_ms": 0
        },
        {
          "job_id": 12866635857,
          "duration_ms": 0
        },
        {
          "job_id": 12866636212,
          "duration_ms": 0
        },
        {
          "job_id": 12866636521,
          "duration_ms": 0
        },
        {
          "job_id": 12866637173,
          "duration_ms": 0
        },
        {
          "job_id": 12866637431,
          "duration_ms": 0
        },
        {
          "job_id": 12866637793,
          "duration_ms": 0
        },
        {
          "job_id": 12866638133,
          "duration_ms": 0
        },
        {
          "job_id": 12866638388,
          "duration_ms": 0
        },
        {
          "job_id": 12866638655,
          "duration_ms": 0
        },
        {
          "job_id": 12866638994,
          "duration_ms": 0
        },
        {
          "job_id": 12866639250,
          "duration_ms": 0
        },
        {
          "job_id": 12866639569,
          "duration_ms": 0
        },
        {
          "job_id": 12866639847,
          "duration_ms": 0
        },
        {
          "job_id": 12866640310,
          "duration_ms": 0
        },
        {
          "job_id": 12866640648,
          "duration_ms": 0
        },
        {
          "job_id": 12866640908,
          "duration_ms": 0
        },
        {
          "job_id": 12866641141,
          "duration_ms": 0
        },
        {
          "job_id": 12866641425,
          "duration_ms": 0
        },
        {
          "job_id": 12866641730,
          "duration_ms": 0
        },
        {
          "job_id": 12866642045,
          "duration_ms": 0
        },
        {
          "job_id": 12868338184,
          "duration_ms": 0
        },
        {
          "job_id": 12868338991,
          "duration_ms": 0
        },
        {
          "job_id": 12868339882,
          "duration_ms": 0
        },
        {
          "job_id": 12868340835,
          "duration_ms": 0
        },
        {
          "job_id": 12868341095,
          "duration_ms": 0
        },
        {
          "job_id": 12868341714,
          "duration_ms": 0
        },
        {
          "job_id": 12868342085,
          "duration_ms": 0
        },
        {
          "job_id": 12868343174,
          "duration_ms": 0
        },
        {
          "job_id": 12868343451,
          "duration_ms": 0
        },
        {
          "job_id": 12868343712,
          "duration_ms": 0
        },
        {
          "job_id": 12868343937,
          "duration_ms": 0
        },
        {
          "job_id": 12868344195,
          "duration_ms": 0
        },
        {
          "job_id": 12868344414,
          "duration_ms": 0
        },
        {
          "job_id": 12868344647,
          "duration_ms": 0
        },
        {
          "job_id": 12868344949,
          "duration_ms": 0
        },
        {
          "job_id": 12868345177,
          "duration_ms": 0
        },
        {
          "job_id": 12868345415,
          "duration_ms": 0
        },
        {
          "job_id": 12868345630,
          "duration_ms": 0
        },
        {
          "job_id": 12868345869,
          "duration_ms": 0
        },
        {
          "job_id": 12868346061,
          "duration_ms": 0
        },
        {
          "job_id": 12868346316,
          "duration_ms": 0
        },
        {
          "job_id": 12868346559,
          "duration_ms": 0
        },
        {
          "job_id": 12868802508,
          "duration_ms": 0
        }
      ]
    }
  },
  "run_duration_ms": 964000
}
