{
  "billable": {
    "UBUNTU": {
      "total_ms": 0,
      "jobs": 30,
      "job_runs": [
        {
          "job_id": 9226073830,
          "duration_ms": 0
        },
        {
          "job_id": 9226074154,
          "duration_ms": 0
        },
        {
          "job_id": 9226081383,
          "duration_ms": 0
        },
        {
          "job_id": 9226130263,
          "duration_ms": 0
        },
        {
          "job_id": 9226130532,
          "duration_ms": 0
        },
        {
          "job_id": 9226130814,
          "duration_ms": 0
        },
        {
          "job_id": 9226131012,
          "duration_ms": 0
        },
        {
          "job_id": 9226131222,
          "duration_ms": 0
        },
        {
          "job_id": 9226131429,
          "duration_ms": 0
        },
        {
          "job_id": 9226131621,
          "duration_ms": 0
        },
        {
          "job_id": 9226131890,
          "duration_ms": 0
        },
        {
          "job_id": 9226132113,
          "duration_ms": 0
        },
        {
          "job_id": 9226132375,
          "duration_ms": 0
        },
        {
          "job_id": 9226132582,
          "duration_ms": 0
        },
        {
          "job_id": 9226132746,
          "duration_ms": 0
        },
        {
          "job_id": 9226132951,
          "duration_ms": 0
        },
        {
          "job_id": 9226133160,
          "duration_ms": 0
        },
        {
          "job_id": 9226133363,
          "duration_ms": 0
        },
        {
          "job_id": 9226133606,
          "duration_ms": 0
        },
        {
          "job_id": 9226133787,
          "duration_ms": 0
        },
        {
          "job_id": 9226133944,
          "duration_ms": 0
        },
        {
          "job_id": 9226134088,
          "duration_ms": 0
        },
        {
          "job_id": 9226134263,
          "duration_ms": 0
        },
        {
          "job_id": 9226134447,
          "duration_ms": 0
        },
        {
          "job_id": 9226134642,
          "duration_ms": 0
        },
        {
          "job_id": 9226640917,
          "duration_ms": 0
        },
        {
          "job_id": 9226641276,
          "duration_ms": 0
        },
        {
          "job_id": 9226652258,
          "duration_ms": 0
        },
        {
          "job_id": 9226652499,
          "duration_ms": 0
        },
        {
          "job_id": 9226668657,
          "duration_ms": 0
        }
      ]
    }
  },
  "run_duration_ms": 1773000
}
