{
  "billable": {
    "UBUNTU": {
      "total_ms": 0,
      "jobs": 10,
      "job_runs": [
        {
          "job_id": 10948829566,
          "duration_ms": 0
        },
        {
          "job_id": 10948864461,
          "duration_ms": 0
        },
        {
          "job_id": 10948864499,
          "duration_ms": 0
        },
        {
          "job_id": 10948864530,
          "duration_ms": 0
        },
        {
          "job_id": 10948864557,
          "duration_ms": 0
        },
        {
          "job_id": 10948864597,
          "duration_ms": 0
        },
        {
          "job_id": 10948864624,
          "duration_ms": 0
        },
        {
          "job_id": 10948864673,
          "duration_ms": 0
        },
        {
          "job_id": 10948864718,
          "duration_ms": 0
        },
        {
          "job_id": 10948864750,
          "duration_ms": 0
        }
      ]
    }
  },
  "run_duration_ms": 2717000
}
