{
  "billable": {
    "UBUNTU": {
      "total_ms": 0,
      "jobs": 26,
      "job_runs": [
        {
          "job_id": 11301109102,
          "duration_ms": 0
        },
        {
          "job_id": 11301109577,
          "duration_ms": 0
        },
        {
          "job_id": 11301109945,
          "duration_ms": 0
        },
        {
          "job_id": 11301110345,
          "duration_ms": 0
        },
        {
          "job_id": 11301124698,
          "duration_ms": 0
        },
        {
          "job_id": 11301125306,
          "duration_ms": 0
        },
        {
          "job_id": 11301125592,
          "duration_ms": 0
        },
        {
          "job_id": 11301125900,
          "duration_ms": 0
        },
        {
          "job_id": 11301126229,
          "duration_ms": 0
        },
        {
          "job_id": 11301126545,
          "duration_ms": 0
        },
        {
          "job_id": 11301126858,
          "duration_ms": 0
        },
        {
          "job_id": 11301127112,
          "duration_ms": 0
        },
        {
          "job_id": 11301127787,
          "duration_ms": 0
        },
        {
          "job_id": 11301128212,
          "duration_ms": 0
        },
        {
          "job_id": 11301128546,
          "duration_ms": 0
        },
        {
          "job_id": 11301128933,
          "duration_ms": 0
        },
        {
          "job_id": 11301129348,
          "duration_ms": 0
        },
        {
          "job_id": 11301130330,
          "duration_ms": 0
        },
        {
          "job_id": 11301130665,
          "duration_ms": 0
        },
        {
          "job_id": 11301130967,
          "duration_ms": 0
        },
        {
          "job_id": 11301213874,
          "duration_ms": 0
        },
        {
          "job_id": 11301478253,
          "duration_ms": 0
        },
        {
          "job_id": 11301478655,
          "duration_ms": 0
        },
        {
          "job_id": 11301478937,
          "duration_ms": 0
        },
        {
          "job_id": 11301958133,
          "duration_ms": 0
        },
        {
          "job_id": 11303225190,
          "duration_ms": 0
        }
      ]
    },
    "MACOS": {
      "total_ms": 0,
      "jobs": 5,
      "job_runs": [
        {
          "job_id": 11301127432,
          "duration_ms": 0
        },
        {
          "job_id": 11301129664,
          "duration_ms": 0
        },
        {
          "job_id": 11301129964,
          "duration_ms": 0
        },
        {
          "job_id": 11301131243,
          "duration_ms": 0
        },
        {
          "job_id": 11301131536,
          "duration_ms": 0
        }
      ]
    }
  },
  "run_duration_ms": 4410000
}
