{
  "billable": {
    "UBUNTU": {
      "total_ms": 0,
      "jobs": 46,
      "job_runs": [
        {
          "job_id": 10044445091,
          "duration_ms": 0
        },
        {
          "job_id": 10044461193,
          "duration_ms": 0
        },
        {
          "job_id": 10044461850,
          "duration_ms": 0
        },
        {
          "job_id": 10044462013,
          "duration_ms": 0
        },
        {
          "job_id": 10044462183,
          "duration_ms": 0
        },
        {
          "job_id": 10044462425,
          "duration_ms": 0
        },
        {
          "job_id": 10044462645,
          "duration_ms": 0
        },
        {
          "job_id": 10044462866,
          "duration_ms": 0
        },
        {
          "job_id": 10044463255,
          "duration_ms": 0
        },
        {
          "job_id": 10044463467,
          "duration_ms": 0
        },
        {
          "job_id": 10044463666,
          "duration_ms": 0
        },
        {
          "job_id": 10044463826,
          "duration_ms": 0
        },
        {
          "job_id": 10044464012,
          "duration_ms": 0
        },
        {
          "job_id": 10044464228,
          "duration_ms": 0
        },
        {
          "job_id": 10044464410,
          "duration_ms": 0
        },
        {
          "job_id": 10044464559,
          "duration_ms": 0
        },
        {
          "job_id": 10044464747,
          "duration_ms": 0
        },
        {
          "job_id": 10044517998,
          "duration_ms": 0
        },
        {
          "job_id": 10044739458,
          "duration_ms": 0
        },
        {
          "job_id": 10044739734,
          "duration_ms": 0
        },
        {
          "job_id": 10044739873,
          "duration_ms": 0
        },
        {
          "job_id": 10044961140,
          "duration_ms": 0
        },
        {
          "job_id": 10048610503,
          "duration_ms": 0
        },
        {
          "job_id": 10048610939,
          "duration_ms": 0
        },
        {
          "job_id": 10048611584,
          "duration_ms": 0
        },
        {
          "job_id": 10048611757,
          "duration_ms": 0
        },
        {
          "job_id": 10048611899,
          "duration_ms": 0
        },
        {
          "job_id": 10048612107,
          "duration_ms": 0
        },
        {
          "job_id": 10048612269,
          "duration_ms": 0
        },
        {
          "job_id": 10048612527,
          "duration_ms": 0
        },
        {
          "job_id": 10048612671,
          "duration_ms": 0
        },
        {
          "job_id": 10048612817,
          "duration_ms": 0
        },
        {
          "job_id": 10048612955,
          "duration_ms": 0
        },
        {
          "job_id": 10048613078,
          "duration_ms": 0
        },
        {
          "job_id": 10048613223,
          "duration_ms": 0
        },
        {
          "job_id": 10048613407,
          "duration_ms": 0
        },
        {
          "job_id": 10048613533,
          "duration_ms": 0
        },
        {
          "job_id": 10048613692,
          "duration_ms": 0
        },
        {
          "job_id": 10048613870,
          "duration_ms": 0
        },
        {
          "job_id": 10048614735,
          "duration_ms": 0
        },
        {
          "job_id": 10048614865,
          "duration_ms": 0
        },
        {
          "job_id": 10048614996,
          "duration_ms": 0
        },
        {
          "job_id": 10048615160,
          "duration_ms": 0
        },
        {
          "job_id": 10048615424,
          "duration_ms": 0
        },
        {
          "job_id": 10049198044,
          "duration_ms": 0
        },
        {
          "job_id": 10049198215,
          "duration_ms": 0
        }
      ]
    },
    "MACOS": {
      "total_ms": 0,
      "jobs": 6,
      "job_runs": [
        {
          "job_id": 10044460708,
          "duration_ms": 0
        },
        {
          "job_id": 10044461425,
          "duration_ms": 0
        },
        {
          "job_id": 10044461653,
          "duration_ms": 0
        },
        {
          "job_id": 10048611126,
          "duration_ms": 0
        },
        {
          "job_id": 10048611283,
          "duration_ms": 0
        },
        {
          "job_id": 10048611411,
          "duration_ms": 0
        }
      ]
    }
  },
  "run_duration_ms": 1773000
}
